platon/__init__.py
platon/__main__.py
platon/cli.py
platon/config.py
platon/git.py
platon/kubectl.py
platon/utils.py
platon/vault.py
platon_cli-1.2.0.dist-info/METADATA
platon_cli-1.2.0.dist-info/WHEEL
platon_cli-1.2.0.dist-info/entry_points.txt
platon_cli-1.2.0.dist-info/top_level.txt
platon_cli-1.2.0.dist-info/RECORD
