Metadata-Version: 2.4
Name: platon-cli
Version: 1.2.0
Summary: Unified CLI tool for managing Vault secrets and Kubernetes resources for Sikt GitLab repositories
Author-email: tollef jørgensen <tollef.jorgensen@sikt.no>
License: MIT
Project-URL: Documentation, https://platon.sikt.no/
Keywords: platon,vault,kubernetes,kubectl,cli
Classifier: Development Status :: 4 - Beta
Classifier: Intended Audience :: Developers
Classifier: Topic :: Software Development :: Build Tools
Classifier: License :: OSI Approved :: MIT License
Classifier: Programming Language :: Python :: 3
Classifier: Programming Language :: Python :: 3.8
Classifier: Programming Language :: Python :: 3.9
Classifier: Programming Language :: Python :: 3.10
Classifier: Programming Language :: Python :: 3.11
Classifier: Programming Language :: Python :: 3.12
Classifier: Programming Language :: Python :: 3.13
Requires-Dist: click>=8.1.0
Requires-Dist: rich>=13.7.0
Requires-Dist: pyyaml>=6.0.1
Requires-Dist: python-dotenv>=1.0.0
Requires-Dist: requests>=2.31.0
Requires-Dist: prompt-toolkit>=3.0.43
Requires-Dist: questionary>=2.0.1
Provides-Extra: dev
Requires-Dist: pytest>=8.0.0; extra == "dev"
Requires-Dist: black>=24.1.0; extra == "dev"
Requires-Dist: flake8>=7.0.0; extra == "dev"
Requires-Dist: mypy>=1.8.0; extra == "dev"
